arc_flow/__init__.py
arc_flow/exceptions.py
arc_flow/agents/__init__.py
arc_flow/agents/agent_factory.py
arc_flow/agents/agent_judge.py
arc_flow/agents/agent_pattern_router.py
arc_flow/agents/agent_registry.py
arc_flow/agents/agent_router.py
arc_flow/agents/mcp_team_builder.py
arc_flow/agents/react_agent.py
arc_flow/agents/reasoning_duo_agent.py
arc_flow/agents/reflexion_agent.py
arc_flow/agents/self_consistency_agent.py
arc_flow/agents/team_builder.py
arc_flow/config/__init__.py
arc_flow/config/config.py
arc_flow/config/settings.py
arc_flow/config/validation.py
arc_flow/core/__init__.py
arc_flow/core/agent_executor.py
arc_flow/core/base.py
arc_flow/core/orchestrator.py
arc_flow/core/state.py
arc_flow/core/supervisor.py
arc_flow/nodes/__init__.py
arc_flow/nodes/coordinator.py
arc_flow/nodes/generator.py
arc_flow/nodes/planner.py
arc_flow/prompts/__init__.py
arc_flow/rl/__init__.py
arc_flow/rl/rewards.py
arc_flow/rl/rl_manager.py
arc_flow/utils/__init__.py
arc_flow/utils/agent_persistence.py
arc_flow/utils/base_structure.py
arc_flow/utils/cached_llm.py
arc_flow/utils/caching.py
arc_flow/utils/conversation.py
arc_flow/utils/decorators.py
arc_flow/utils/helpers.py
arc_flow/utils/logging.py
arc_flow/utils/output_formatter.py
arc_flow/utils/prompts.py
arc_flow/utils/retry.py
arc_flow/workflows/__init__.py
arc_flow/workflows/agent_rearrange.py
arc_flow/workflows/concurrent_workflow.py
arc_flow/workflows/forest_swarm.py
arc_flow/workflows/graph_workflow.py
arc_flow/workflows/group_chat.py
arc_flow/workflows/heavy_swarm.py
arc_flow/workflows/hierarchical_swarm.py
arc_flow/workflows/mixture_of_agents.py
arc_flow/workflows/sequential_workflow.py
arc_flow/workflows/swarm_router.py
arc_flow-0.1.1.dist-info/METADATA
arc_flow-0.1.1.dist-info/WHEEL
arc_flow-0.1.1.dist-info/entry_points.txt
arc_flow-0.1.1.dist-info/top_level.txt
arc_flow-0.1.1.dist-info/RECORD
